[
    {
        "name":"算了呢1",
        "img":"image/shouji1.png"
    },
    {
        "name":"算了呢2",
        "img":"image/shouji1.png"
    },
    {
        "name":"算了呢3",
        "img":"image/shouji1.png"
    },
    {
        "name":"算了呢4",
        "img":"image/shouji1.png"
    },
    {
        "name":"算了呢5",
        "img":"image/shouji1.png"
    },
    {
        "name":"算了呢6",
        "img":"image/shouji2.png"
    },
    {
        "name":"算了呢7",
        "img":"image/shouji2.png"
    },
    {
        "name":"算了呢8",
        "img":"image/shouji2.png"
    },
    {
        "name":"算了呢9",
        "img":"image/shouji2.png"
    },
    {
        "name":"算了呢10",
        "img":"image/shouji2.png"
    }
]